obey/__init__.py
obey-0.0.1.dist-info/WHEEL
obey-0.0.1.dist-info/METADATA
obey-0.0.1.dist-info/RECORD
